[
    {
        "point_1": [
            47.06673,
            2.44453,
            464.6
        ],
        "point_2": [
            47.07094,
            2.45144,
            708.5
        ],
        "gh_interp": 0.8541706963026235,
        "u_interp": 19.921814455880412,
        "v_interp": -16.02109369102091,
        "w_interp": -0.00439055141705502
    },
    {
        "point_1": [
            47.07094,
            2.45144,
            708.5
        ],
        "point_2": [
            47.07412,
            2.45958,
            942.7
        ],
        "gh_interp": 0.9653648276314154,
        "u_interp": 21.69172883973425,
        "v_interp": -14.234575955848031,
        "w_interp": -0.0054403962200489
    },
    {
        "point_1": [
            47.07412,
            2.45958,
            942.7
        ],
        "point_2": [
            47.07586,
            2.46895,
            1169.1
        ],
        "gh_interp": 0.0024100077307641866,
        "u_interp": 22.45685613373692,
        "v_interp": -12.530674502002194,
        "w_interp": -0.007189003960710653
    },
    {
        "point_1": [
            47.07586,
            2.46895,
            1169.1
        ],
        "point_2": [
            47.07804,
            2.47685,
            1479.3
        ],
        "gh_interp": 0.48565931536228135,
        "u_interp": 23.24670248382354,
        "v_interp": -11.805257644585156,
        "w_interp": -0.009282289829319858
    },
    {
        "point_1": [
            47.07804,
            2.47685,
            1479.3
        ],
        "point_2": [
            47.0816,
            2.48603,
            1892.0
        ],
        "gh_interp": 0.14002649613544524,
        "u_interp": 23.9835758653332,
        "v_interp": -11.12432484305668,
        "w_interp": -0.012314995903690196
    },
    {
        "point_1": [
            47.0816,
            2.48603,
            1892.0
        ],
        "point_2": [
            47.0857,
            2.49813,
            2293.0
        ],
        "gh_interp": 0.9747185587998426,
        "u_interp": 23.364886610846856,
        "v_interp": -11.667702230736348,
        "w_interp": -0.017112029286308797
    },
    {
        "point_1": [
            47.0857,
            2.49813,
            2293.0
        ],
        "point_2": [
            47.09049,
            2.51044,
            2695.7
        ],
        "gh_interp": 0.7456544771010448,
        "u_interp": 23.436433100729616,
        "v_interp": -11.692883437605476,
        "w_interp": -0.022802546150583018
    },
    {
        "point_1": [
            47.09049,
            2.51044,
            2695.7
        ],
        "point_2": [
            47.09534,
            2.52247,
            3053.5
        ],
        "gh_interp": 0.4918953396580658,
        "u_interp": 23.439580620461037,
        "v_interp": -11.758718951815453,
        "w_interp": -0.01950248138387725
    },
    {
        "point_1": [
            47.09534,
            2.52247,
            3053.5
        ],
        "point_2": [
            47.10075,
            2.53503,
            3432.6
        ],
        "gh_interp": 0.13475404656263687,
        "u_interp": 23.86544404494485,
        "v_interp": -12.046955494328062,
        "w_interp": -0.01076682128748109
    },
    {
        "point_1": [
            47.10075,
            2.53503,
            3432.6
        ],
        "point_2": [
            47.10662,
            2.54657,
            3718.2
        ],
        "gh_interp": 0.7837394384798765,
        "u_interp": 26.053982299683952,
        "v_interp": -13.122409432417784,
        "w_interp": 0.00547790449837577
    },
    {
        "point_1": [
            47.10662,
            2.54657,
            3718.2
        ],
        "point_2": [
            47.11434,
            2.55946,
            4161.8
        ],
        "gh_interp": 0.255087998767536,
        "u_interp": 27.202709327593812,
        "v_interp": -14.01215666311258,
        "w_interp": 0.0068518298409087925
    },
    {
        "point_1": [
            47.11434,
            2.55946,
            4161.8
        ],
        "point_2": [
            47.1223,
            2.57396,
            4436.6
        ],
        "gh_interp": 0.9655476349952437,
        "u_interp": 28.370923855210656,
        "v_interp": -15.49211874564581,
        "w_interp": -0.004398201377248908
    },
    {
        "point_1": [
            47.1223,
            2.57396,
            4436.6
        ],
        "point_2": [
            47.13072,
            2.58885,
            4666.2
        ],
        "gh_interp": 0.38089219865863333,
        "u_interp": 28.26928559828998,
        "v_interp": -15.914605356909654,
        "w_interp": -0.014027843101547834
    },
    {
        "point_1": [
            47.13072,
            2.58885,
            4666.2
        ],
        "point_2": [
            47.14014,
            2.60222,
            4889.0
        ],
        "gh_interp": 0.739570518792374,
        "u_interp": 28.788535723722415,
        "v_interp": -16.462807505884363,
        "w_interp": 0.04091671749933559
    },
    {
        "point_1": [
            47.14014,
            2.60222,
            4889.0
        ],
        "point_2": [
            47.14986,
            2.61558,
            5098.0
        ],
        "gh_interp": 0.06955345707894332,
        "u_interp": 29.394350632115653,
        "v_interp": -16.131053048689484,
        "w_interp": 0.03647490422727734
    },
    {
        "point_1": [
            47.14986,
            2.61558,
            5098.0
        ],
        "point_2": [
            47.15973,
            2.62733,
            5321.0
        ],
        "gh_interp": 0.36192004917948806,
        "u_interp": 30.118814601843802,
        "v_interp": -15.611443044004197,
        "w_interp": 0.035920749934679724
    },
    {
        "point_1": [
            47.15973,
            2.62733,
            5321.0
        ],
        "point_2": [
            47.16959,
            2.63829,
            5562.2
        ],
        "gh_interp": 0.6695416538684686,
        "u_interp": 31.23225885527349,
        "v_interp": -15.399432739076067,
        "w_interp": 0.040873365979408376
    },
    {
        "point_1": [
            47.16959,
            2.63829,
            5562.2
        ],
        "point_2": [
            47.1809,
            2.64925,
            5822.6
        ],
        "gh_interp": 0.006197657895532231,
        "u_interp": 32.62970049270945,
        "v_interp": -14.593523262131848,
        "w_interp": 0.05177048045403799
    },
    {
        "point_1": [
            47.1809,
            2.64925,
            5822.6
        ],
        "point_2": [
            47.19287,
            2.66083,
            6072.2
        ],
        "gh_interp": 0.34210623116692074,
        "u_interp": 35.869162107161046,
        "v_interp": -14.924755724712126,
        "w_interp": 0.03871662665007618
    },
    {
        "point_1": [
            47.19287,
            2.66083,
            6072.2
        ],
        "point_2": [
            47.20634,
            2.67364,
            6322.8
        ],
        "gh_interp": 0.6640831124593103,
        "u_interp": 38.974268170782835,
        "v_interp": -15.24225043538815,
        "w_interp": 0.026204176920933114
    },
    {
        "point_1": [
            47.20634,
            2.67364,
            6322.8
        ],
        "point_2": [
            47.22323,
            2.68739,
            6628.4
        ],
        "gh_interp": 0.9873499652312377,
        "u_interp": 42.091814563185174,
        "v_interp": -15.561017160129385,
        "w_interp": 0.013641597184862346
    },
    {
        "point_1": [
            47.22323,
            2.68739,
            6628.4
        ],
        "point_2": [
            47.24114,
            2.70061,
            6866.5
        ],
        "gh_interp": 0.3476854362847137,
        "u_interp": 40.729045774017706,
        "v_interp": -19.279050852773544,
        "w_interp": 0.013614452036543443
    },
    {
        "point_1": [
            47.24114,
            2.70061,
            6866.5
        ],
        "point_2": [
            47.26213,
            2.71127,
            7116.7
        ],
        "gh_interp": 0.627555977976706,
        "u_interp": 39.53387992690403,
        "v_interp": -22.26185343243649,
        "w_interp": 0.013988314228451768
    },
    {
        "point_1": [
            47.26213,
            2.71127,
            7116.7
        ],
        "point_2": [
            47.28147,
            2.71977,
            7331.5
        ],
        "gh_interp": 0.9216492561427552,
        "u_interp": 38.27797696618231,
        "v_interp": -25.396239007537986,
        "w_interp": 0.014381175716966942
    },
    {
        "point_1": [
            47.28147,
            2.71977,
            7331.5
        ],
        "point_2": [
            47.2948,
            2.72638,
            7473.8999
        ],
        "gh_interp": 0.15798726195578083,
        "u_interp": 39.013666247073616,
        "v_interp": -25.45081618464425,
        "w_interp": 9.29995196457551e-05
    },
    {
        "point_1": [
            47.2948,
            2.72638,
            7473.8999
        ],
        "point_2": [
            47.30622,
            2.73152,
            7600.5
        ],
        "gh_interp": 0.30984972065555505,
        "u_interp": 40.04245411249478,
        "v_interp": -24.700604261032595,
        "w_interp": -0.01374186335889397
    },
    {
        "point_1": [
            47.30622,
            2.73152,
            7600.5
        ],
        "point_2": [
            47.31883,
            2.7368,
            7731.2
        ],
        "gh_interp": 0.4448624731760076,
        "u_interp": 40.957094127277834,
        "v_interp": -24.033631148337804,
        "w_interp": -0.026041696602522715
    },
    {
        "point_1": [
            47.31883,
            2.7368,
            7731.2
        ],
        "point_2": [
            47.33712,
            2.74479,
            7930.1001
        ],
        "gh_interp": 0.5842475665086603,
        "u_interp": 41.90135443933245,
        "v_interp": -23.345058344452106,
        "w_interp": -0.038739855647754735
    },
    {
        "point_1": [
            47.33712,
            2.74479,
            7930.1001
        ],
        "point_2": [
            47.35285,
            2.75135,
            8099.7
        ],
        "gh_interp": 0.7963646973607947,
        "u_interp": 43.338335850913886,
        "v_interp": -22.297183826088332,
        "w_interp": -0.05806399569299234
    },
    {
        "point_1": [
            47.35285,
            2.75135,
            8099.7
        ],
        "point_2": [
            47.37644,
            2.76174,
            8354.7998
        ],
        "gh_interp": 0.977234612362391,
        "u_interp": 44.563633896043434,
        "v_interp": -21.40367289508807,
        "w_interp": -0.07454147468500039
    },
    {
        "point_1": [
            47.37644,
            2.76174,
            8354.7998
        ],
        "point_2": [
            47.39459,
            2.77043,
            8532.7
        ],
        "gh_interp": 0.23503603230711498,
        "u_interp": 45.03685915616138,
        "v_interp": -24.22002220051906,
        "w_interp": -0.12562777330770855
    },
    {
        "point_1": [
            47.39459,
            2.77043,
            8532.7
        ],
        "point_2": [
            47.42407,
            2.78037,
            8808.6
        ],
        "gh_interp": 0.4057059288108002,
        "u_interp": 45.48634552703521,
        "v_interp": -23.514799219132552,
        "w_interp": -0.13013882466002907
    },
    {
        "point_1": [
            47.42407,
            2.78037,
            8808.6
        ],
        "point_2": [
            47.44345,
            2.78555,
            8981.90039
        ],
        "gh_interp": 0.6703926714078668,
        "u_interp": 46.18344024488315,
        "v_interp": -22.421090383703827,
        "w_interp": -0.1371348767617424
    },
    {
        "point_1": [
            47.44345,
            2.78555,
            8981.90039
        ],
        "point_2": [
            47.4581,
            2.78946,
            9116.5
        ],
        "gh_interp": 0.8366497055503149,
        "u_interp": 46.6213046394826,
        "v_interp": -21.73410173663516,
        "w_interp": -0.1415292898015657
    },
    {
        "point_1": [
            47.4581,
            2.78946,
            9116.5
        ],
        "point_2": [
            47.47191,
            2.79303,
            9240.59961
        ],
        "gh_interp": 0.9657788549730603,
        "u_interp": 46.9613868328693,
        "v_interp": -21.200528765622984,
        "w_interp": -0.1449423593355646
    },
    {
        "point_1": [
            47.47191,
            2.79303,
            9240.59961
        ],
        "point_2": [
            47.48605,
            2.79678,
            9366.2998
        ],
        "gh_interp": 0.0749284861965126,
        "u_interp": 47.61796312638705,
        "v_interp": -21.314447045627603,
        "w_interp": -0.1383471539966234
    },
    {
        "point_1": [
            47.48605,
            2.79678,
            9366.2998
        ],
        "point_2": [
            47.50125,
            2.80077,
            9499.9
        ],
        "gh_interp": 0.1814382926258116,
        "u_interp": 48.423163188668155,
        "v_interp": -21.67738523244097,
        "w_interp": -0.12768640645654716
    },
    {
        "point_1": [
            47.50125,
            2.80077,
            9499.9
        ],
        "point_2": [
            47.51604,
            2.80407,
            9627.0
        ],
        "gh_interp": 0.29464203114772924,
        "u_interp": 49.278968493025815,
        "v_interp": -22.06313337129344,
        "w_interp": -0.11635565187691076
    },
    {
        "point_1": [
            47.51604,
            2.80407,
            9627.0
        ],
        "point_2": [
            47.53126,
            2.80691,
            9761.2998
        ],
        "gh_interp": 0.40233794152912,
        "u_interp": 50.09313534445164,
        "v_interp": -22.430113274378538,
        "w_interp": -0.10557618517647319
    },
    {
        "point_1": [
            47.53126,
            2.80691,
            9761.2998
        ],
        "point_2": [
            47.54679,
            2.80982,
            9897.09961
        ],
        "gh_interp": 0.5161344735907938,
        "u_interp": 50.953422089637456,
        "v_interp": -22.817881390730612,
        "w_interp": -0.09418609688398355
    },
    {
        "point_1": [
            47.54679,
            2.80982,
            9897.09961
        ],
        "point_2": [
            47.56259,
            2.81295,
            10020.8
        ],
        "gh_interp": 0.6312020122813501,
        "u_interp": 51.823317476985395,
        "v_interp": -23.20998053402545,
        "w_interp": -0.08266879137791958
    },
    {
        "point_1": [
            47.56259,
            2.81295,
            10020.8
        ],
        "point_2": [
            47.5786,
            2.8163,
            10144.7002
        ],
        "gh_interp": 0.736017323969651,
        "u_interp": 52.615707382936975,
        "v_interp": -23.567144634212617,
        "w_interp": -0.07217764869628197
    },
    {
        "point_1": [
            47.5786,
            2.8163,
            10144.7002
        ],
        "point_2": [
            47.59485,
            2.8196,
            10276.2
        ],
        "gh_interp": 0.841001941085594,
        "u_interp": 53.40937721554933,
        "v_interp": -23.924885652215956,
        "w_interp": -0.06166955994665528
    },
    {
        "point_1": [
            47.59485,
            2.8196,
            10276.2
        ],
        "point_2": [
            47.61144,
            2.8234,
            10443.3
        ],
        "gh_interp": 0.9524259432568838,
        "u_interp": 54.25172794827258,
        "v_interp": -24.30456923883838,
        "w_interp": -0.05051694220303439
    },
    {
        "point_1": [
            47.61144,
            2.8234,
            10443.3
        ],
        "point_2": [
            47.62911,
            2.82944,
            10655.59961
        ],
        "gh_interp": 0.08024555944087995,
        "u_interp": 55.10276068843051,
        "v_interp": -23.708117564209896,
        "w_interp": -0.03610164886169148
    },
    {
        "point_1": [
            47.62911,
            2.82944,
            10655.59961
        ],
        "point_2": [
            47.64719,
            2.83683,
            10796.40039
        ],
        "gh_interp": 0.24364642569622405,
        "u_interp": 55.80588078741509,
        "v_interp": -21.17514332289748,
        "w_interp": 0.09416251143803087
    },
    {
        "point_1": [
            47.64719,
            2.83683,
            10796.40039
        ],
        "point_2": [
            47.66583,
            2.84436,
            10920.8
        ],
        "gh_interp": 0.34557225604040326,
        "u_interp": 56.38924737360502,
        "v_interp": -20.425680585770632,
        "w_interp": 0.08224736172047341
    },
    {
        "point_1": [
            47.66583,
            2.84436,
            10920.8
        ],
        "point_2": [
            47.68469,
            2.8519,
            11046.8
        ],
        "gh_interp": 0.4356252624494713,
        "u_interp": 56.90466053970437,
        "v_interp": -19.76351896842654,
        "w_interp": 0.07172014746813954
    },
    {
        "point_1": [
            47.68469,
            2.8519,
            11046.8
        ],
        "point_2": [
            47.70381,
            2.85992,
            11174.9
        ],
        "gh_interp": 0.5268367928356414,
        "u_interp": 57.42670445068222,
        "v_interp": -19.0928387003344,
        "w_interp": 0.06105750153384694
    },
    {
        "point_1": [
            47.70381,
            2.85992,
            11174.9
        ],
        "point_2": [
            47.72249,
            2.86877,
            11309.1
        ],
        "gh_interp": 0.6195685153949146,
        "u_interp": 57.9574490935097,
        "v_interp": -18.41098042777406,
        "w_interp": 0.05021714483398278
    },
    {
        "point_1": [
            47.72249,
            2.86877,
            11309.1
        ],
        "point_2": [
            47.73915,
            2.8781,
            11466.2002
        ],
        "gh_interp": 0.7167160342665344,
        "u_interp": 58.51346729075753,
        "v_interp": -17.696652713663227,
        "w_interp": 0.038860580672220285
    },
    {
        "point_1": [
            47.73915,
            2.8781,
            11466.2002
        ],
        "point_2": [
            47.75307,
            2.88732,
            11633.2002
        ],
        "gh_interp": 0.8283223211880799,
        "u_interp": 59.003741819177556,
        "v_interp": -15.50733834620184,
        "w_interp": 0.0303499841513779
    },
    {
        "point_1": [
            47.75307,
            2.88732,
            11633.2002
        ],
        "point_2": [
            47.76535,
            2.89543,
            11774.90039
        ],
        "gh_interp": 0.9492172980600441,
        "u_interp": 59.65940881595543,
        "v_interp": -14.66675291193788,
        "w_interp": 0.024994313122017525
    },
    {
        "point_1": [
            47.76535,
            2.89543,
            11774.90039
        ],
        "point_2": [
            47.77596,
            2.90388,
            11903.59961
        ],
        "gh_interp": 0.039822248542836974,
        "u_interp": 59.20867355094514,
        "v_interp": -14.197992073071783,
        "w_interp": 0.022385047039810105
    },
    {
        "point_1": [
            47.77596,
            2.90388,
            11903.59961
        ],
        "point_2": [
            47.78476,
            2.91094,
            12015.2002
        ],
        "gh_interp": 0.11145098943624422,
        "u_interp": 57.902534893197554,
        "v_interp": -13.989939426930366,
        "w_interp": 0.02173826183524678
    },
    {
        "point_1": [
            47.78476,
            2.91094,
            12015.2002
        ],
        "point_2": [
            47.79313,
            2.91939,
            12132.9
        ],
        "gh_interp": 0.17356332970265348,
        "u_interp": 56.76992628199975,
        "v_interp": -13.80952809218845,
        "w_interp": 0.021177406762212626
    },
    {
        "point_1": [
            47.79313,
            2.91939,
            12132.9
        ],
        "point_2": [
            47.80154,
            2.92797,
            12251.2002
        ],
        "gh_interp": 0.23907024169020066,
        "u_interp": 55.57541819726418,
        "v_interp": -13.61925689365037,
        "w_interp": 0.020585899764578426
    },
    {
        "point_1": [
            47.80154,
            2.92797,
            12251.2002
        ],
        "point_2": [
            47.80959,
            2.93665,
            12372.5
        ],
        "gh_interp": 0.3049113118492764,
        "u_interp": 54.374816791604744,
        "v_interp": -13.428015100195376,
        "w_interp": 0.019991375422807878
    },
    {
        "point_1": [
            47.80959,
            2.93665,
            12372.5
        ],
        "point_2": [
            47.8164,
            2.94497,
            12493.0
        ],
        "gh_interp": 0.37242183712380617,
        "u_interp": 53.14377313837162,
        "v_interp": -13.231924211948927,
        "w_interp": 0.019381776421691227
    },
    {
        "point_1": [
            47.8164,
            2.94497,
            12493.0
        ],
        "point_2": [
            47.82281,
            2.95378,
            12623.8
        ],
        "gh_interp": 0.43948722631307763,
        "u_interp": 51.92084647060637,
        "v_interp": -13.037126264766021,
        "w_interp": 0.0187761968606816
    },
    {
        "point_1": [
            47.82281,
            2.95378,
            12623.8
        ],
        "point_2": [
            47.82883,
            2.9608,
            12745.2998
        ],
        "gh_interp": 0.5122851757401038,
        "u_interp": 50.59338748186203,
        "v_interp": -12.825677538695285,
        "w_interp": 0.01811885406748609
    },
    {
        "point_1": [
            47.82883,
            2.9608,
            12745.2998
        ],
        "point_2": [
            47.83437,
            2.96774,
            12867.59961
        ],
        "gh_interp": 0.5799070128639108,
        "u_interp": 49.36031407482348,
        "v_interp": -12.629263334353926,
        "w_interp": 0.017508249955064857
    },
    {
        "point_1": [
            47.83437,
            2.96774,
            12867.59961
        ],
        "point_2": [
            47.83946,
            2.97501,
            12996.2998
        ],
        "gh_interp": 0.6479741029504158,
        "u_interp": 48.11912155107559,
        "v_interp": -12.43155584946713,
        "w_interp": 0.016893625347169754
    },
    {
        "point_1": [
            47.83946,
            2.97501,
            12996.2998
        ],
        "point_2": [
            47.8443,
            2.98236,
            13122.59961
        ],
        "gh_interp": 0.7196033837062936,
        "u_interp": 46.812973049022006,
        "v_interp": -12.223501635242648,
        "w_interp": 0.016246835267816586
    },
    {
        "point_1": [
            47.8443,
            2.98236,
            13122.59961
        ],
        "point_2": [
            47.84896,
            2.99036,
            13245.7998
        ],
        "gh_interp": 0.7898967107783347,
        "u_interp": 45.531185449165726,
        "v_interp": -12.019327828457664,
        "w_interp": 0.015612108433829876
    },
    {
        "point_1": [
            47.84896,
            2.99036,
            13245.7998
        ],
        "point_2": [
            47.85358,
            2.99807,
            13366.1
        ],
        "gh_interp": 0.8584649156791005,
        "u_interp": 44.280855176761186,
        "v_interp": -11.82016480684319,
        "w_interp": 0.014992958915352666
    },
    {
        "point_1": [
            47.85358,
            2.99807,
            13366.1
        ],
        "point_2": [
            47.85809,
            3.00684,
            13491.4
        ],
        "gh_interp": 0.9254191043309442,
        "u_interp": 43.05995623304756,
        "v_interp": -11.6256898524391,
        "w_interp": 0.014388383460536317
    },
    {
        "point_1": [
            47.85809,
            3.00684,
            13491.4
        ],
        "point_2": [
            47.86217,
            3.01557,
            13611.1
        ],
        "gh_interp": 0.9951559779028585,
        "u_interp": 41.78831547395225,
        "v_interp": -11.423132318978372,
        "w_interp": 0.013758681228216765
    },
    {
        "point_1": [
            47.86217,
            3.01557,
            13611.1
        ],
        "point_2": [
            47.86581,
            3.02332,
            13738.9
        ],
        "gh_interp": 0.04375063993650304,
        "u_interp": 41.769725103021344,
        "v_interp": -10.990633022365076,
        "w_interp": 0.013052198070967498
    },
    {
        "point_1": [
            47.86581,
            3.02332,
            13738.9
        ],
        "point_2": [
            47.8691,
            3.03005,
            13856.09961
        ],
        "gh_interp": 0.09412459380872486,
        "u_interp": 41.85002242762485,
        "v_interp": -10.508858550702278,
        "w_interp": 0.012289123684143605
    },
    {
        "point_1": [
            47.8691,
            3.03005,
            13856.09961
        ],
        "point_2": [
            47.87202,
            3.03794,
            13975.90039
        ],
        "gh_interp": 0.1403202725879299,
        "u_interp": 41.92365947870133,
        "v_interp": -10.067044934216863,
        "w_interp": 0.01158934261578093
    },
    {
        "point_1": [
            47.87202,
            3.03794,
            13975.90039
        ],
        "point_2": [
            47.8742,
            3.04514,
            14099.5
        ],
        "gh_interp": 0.1875412347598884,
        "u_interp": 41.99893085678752,
        "v_interp": -9.615425548541653,
        "w_interp": 0.010874030356473217
    },
    {
        "point_1": [
            47.8742,
            3.04514,
            14099.5
        ],
        "point_2": [
            47.87648,
            3.05127,
            14231.0
        ],
        "gh_interp": 0.23625955285663805,
        "u_interp": 42.07658905713992,
        "v_interp": -9.149485510940107,
        "w_interp": 0.010136035860288379
    },
    {
        "point_1": [
            47.87648,
            3.05127,
            14231.0
        ],
        "point_2": [
            47.87891,
            3.0565,
            14356.09961
        ],
        "gh_interp": 0.2934226491172224,
        "u_interp": 42.30249620657897,
        "v_interp": -8.13589908853417,
        "w_interp": 0.0208839427414025
    },
    {
        "point_1": [
            47.87891,
            3.0565,
            14356.09961
        ],
        "point_2": [
            47.88252,
            3.06111,
            14489.1
        ],
        "gh_interp": 0.3426716617072414,
        "u_interp": 42.37509051813244,
        "v_interp": -7.693940446798091,
        "w_interp": 0.020408778778933608
    },
    {
        "point_1": [
            47.88252,
            3.06111,
            14489.1
        ],
        "point_2": [
            47.88665,
            3.06538,
            14616.5
        ],
        "gh_interp": 0.3950310406180752,
        "u_interp": 42.45226958966106,
        "v_interp": -7.224069503836963,
        "w_interp": 0.01990360540291502
    },
    {
        "point_1": [
            47.88665,
            3.06538,
            14616.5
        ],
        "point_2": [
            47.89124,
            3.06934,
            14754.2998
        ],
        "gh_interp": 0.4451856670311267,
        "u_interp": 42.52619879928778,
        "v_interp": -6.7739839203792975,
        "w_interp": 0.019419703903793342
    },
    {
        "point_1": [
            47.89124,
            3.06934,
            14754.2998
        ],
        "point_2": [
            47.89588,
            3.07264,
            14891.9
        ],
        "gh_interp": 0.4994344699258934,
        "u_interp": 42.60616293037664,
        "v_interp": -6.287157363210143,
        "w_interp": 0.018896301001135037
    },
    {
        "point_1": [
            47.89588,
            3.07264,
            14891.9
        ],
        "point_2": [
            47.89996,
            3.07658,
            15026.7998
        ],
        "gh_interp": 0.5536046946147564,
        "u_interp": 42.68601123516847,
        "v_interp": -5.801035963674105,
        "w_interp": 0.018373656236147264
    },
    {
        "point_1": [
            47.89996,
            3.07658,
            15026.7998
        ],
        "point_2": [
            47.90385,
            3.08026,
            15160.3
        ],
        "gh_interp": 0.6067118301892889,
        "u_interp": 42.76429251925641,
        "v_interp": -5.324454682737503,
        "w_interp": 0.017861268359764097
    },
    {
        "point_1": [
            47.90385,
            3.08026,
            15160.3
        ],
        "point_2": [
            47.90715,
            3.08364,
            15278.7002
        ],
        "gh_interp": 0.6592679734943722,
        "u_interp": 42.84176162656418,
        "v_interp": -4.852817984081971,
        "w_interp": 0.01735419656295842
    },
    {
        "point_1": [
            47.90715,
            3.08364,
            15278.7002
        ],
        "point_2": [
            47.90995,
            3.08765,
            15391.2
        ],
        "gh_interp": 0.7058795731665118,
        "u_interp": 42.910468323625764,
        "v_interp": -4.4345273789131765,
        "w_interp": 0.016904478868481915
    },
    {
        "point_1": [
            47.90995,
            3.08765,
            15391.2
        ],
        "point_2": [
            47.91219,
            3.09187,
            15505.7
        ],
        "gh_interp": 0.7501683128882002,
        "u_interp": 42.97575106536175,
        "v_interp": -4.037082024738361,
        "w_interp": 0.016477172574361904
    },
    {
        "point_1": [
            47.91219,
            3.09187,
            15505.7
        ],
        "point_2": [
            47.91446,
            3.0956,
            15625.6
        ],
        "gh_interp": 0.7952444881181407,
        "u_interp": 43.04219450729472,
        "v_interp": -3.6325702562461872,
        "w_interp": 0.016042268950739985
    },
    {
        "point_1": [
            47.91446,
            3.0956,
            15625.6
        ],
        "point_2": [
            47.91684,
            3.09899,
            15748.0
        ],
        "gh_interp": 0.8424465266340345,
        "u_interp": 43.11177152640182,
        "v_interp": -3.208981076838228,
        "w_interp": 0.015586854588536774
    },
    {
        "point_1": [
            47.91684,
            3.09899,
            15748.0
        ],
        "point_2": [
            47.91958,
            3.10224,
            15881.7002
        ],
        "gh_interp": 0.8906327611156476,
        "u_interp": 43.18279927568212,
        "v_interp": -2.7765597627470315,
        "w_interp": 0.015121944514027407
    },
    {
        "point_1": [
            47.91958,
            3.10224,
            15881.7002
        ],
        "point_2": [
            47.9226,
            3.10528,
            16021.59961
        ],
        "gh_interp": 0.9432676400979887,
        "u_interp": 43.260384441403744,
        "v_interp": -2.30421649331684,
        "w_interp": 0.014614113060237233
    },
    {
        "point_1": [
            47.9226,
            3.10528,
            16021.59961
        ],
        "point_2": [
            47.92648,
            3.10889,
            16165.09961
        ],
        "gh_interp": 0.9983430140693886,
        "u_interp": 43.341566959524194,
        "v_interp": -1.8099723208267804,
        "w_interp": 0.014082735240572882
    },
    {
        "point_1": [
            47.92648,
            3.10889,
            16165.09961
        ],
        "point_2": [
            47.93074,
            3.11317,
            16302.90039
        ],
        "gh_interp": 0.06259138561671576,
        "u_interp": 43.299133106511455,
        "v_interp": -1.655794583942862,
        "w_interp": 0.014206484835623865
    },
    {
        "point_1": [
            47.93074,
            3.11317,
            16302.90039
        ],
        "point_2": [
            47.93456,
            3.11835,
            16436.9
        ],
        "gh_interp": 0.12451312322385555,
        "u_interp": 43.25473693271666,
        "v_interp": -1.5179769896892537,
        "w_interp": 0.01434472634767747
    },
    {
        "point_1": [
            47.93456,
            3.11835,
            16436.9
        ],
        "point_2": [
            47.93704,
            3.12334,
            16563.40039
        ],
        "gh_interp": 0.18472677868994963,
        "u_interp": 43.21156540659036,
        "v_interp": -1.3839610292489595,
        "w_interp": 0.01447915453234372
    },
    {
        "point_1": [
            47.93704,
            3.12334,
            16563.40039
        ],
        "point_2": [
            47.93964,
            3.12841,
            16692.9
        ],
        "gh_interp": 0.2415706075621854,
        "u_interp": 43.17080995295977,
        "v_interp": -1.2574452038527413,
        "w_interp": 0.01460605951204681
    },
    {
        "point_1": [
            47.93964,
            3.12841,
            16692.9
        ],
        "point_2": [
            47.94197,
            3.1331,
            16818.59961
        ],
        "gh_interp": 0.29971925559318174,
        "u_interp": 43.262285946826715,
        "v_interp": -0.8157837971092238,
        "w_interp": 0.00648262651110984
    },
    {
        "point_1": [
            47.94197,
            3.1331,
            16818.59961
        ],
        "point_2": [
            47.9444,
            3.13729,
            16951.40039
        ],
        "gh_interp": 0.35616475628912253,
        "u_interp": 43.18851322946168,
        "v_interp": -0.7386976534204832,
        "w_interp": 0.009272869895767717
    },
    {
        "point_1": [
            47.9444,
            3.13729,
            16951.40039
        ],
        "point_2": [
            47.9471,
            3.14055,
            17089.5
        ],
        "gh_interp": 0.4157990425045799,
        "u_interp": 43.11057285710256,
        "v_interp": -0.6572566687662216,
        "w_interp": 0.012220742986801175
    },
    {
        "point_1": [
            47.9471,
            3.14055,
            17089.5
        ],
        "point_2": [
            47.95006,
            3.14256,
            17237.1
        ],
        "gh_interp": 0.47781277216025847,
        "u_interp": 43.02952261759305,
        "v_interp": -0.5725661404517809,
        "w_interp": 0.015286237965077852
    },
    {
        "point_1": [
            47.95006,
            3.14256,
            17237.1
        ],
        "point_2": [
            47.95269,
            3.14542,
            17387.30078
        ],
        "gh_interp": 0.5440926588100324,
        "u_interp": 42.94289662819595,
        "v_interp": -0.4820494331329751,
        "w_interp": 0.01856261983750768
    },
    {
        "point_1": [
            47.95269,
            3.14542,
            17387.30078
        ],
        "point_2": [
            47.95506,
            3.14889,
            17539.59961
        ],
        "gh_interp": 0.6115404275980265,
        "u_interp": 42.85474424895669,
        "v_interp": -0.3899377797297453,
        "w_interp": 0.021896733067974045
    },
    {
        "point_1": [
            47.95506,
            3.14889,
            17539.59961
        ],
        "point_2": [
            47.95803,
            3.15268,
            17680.5
        ],
        "gh_interp": 0.6799303272544851,
        "u_interp": 42.76536053057749,
        "v_interp": -0.29653948284555376,
        "w_interp": 0.025277418202149363
    },
    {
        "point_1": [
            47.95803,
            3.15268,
            17680.5
        ],
        "point_2": [
            47.96153,
            3.15762,
            17825.30078
        ],
        "gh_interp": 0.7432017491928927,
        "u_interp": 42.68266652183638,
        "v_interp": -0.21013135708176245,
        "w_interp": 0.028405084080294983
    },
    {
        "point_1": [
            47.96153,
            3.15762,
            17825.30078
        ],
        "point_2": [
            47.96571,
            3.1638,
            17947.09961
        ],
        "gh_interp": 0.8082246440790651,
        "u_interp": 42.59768338611165,
        "v_interp": -0.12133129053166058,
        "w_interp": 0.03161932968128217
    },
    {
        "point_1": [
            47.96571,
            3.1638,
            17947.09961
        ],
        "point_2": [
            47.96955,
            3.1707,
            18051.0
        ],
        "gh_interp": 0.8629184966974605,
        "u_interp": 42.52620002462005,
        "v_interp": -0.04663732679939048,
        "w_interp": 0.034322984685991965
    },
    {
        "point_1": [
            47.96955,
            3.1707,
            18051.0
        ],
        "point_2": [
            47.97224,
            3.177,
            18148.19922
        ],
        "gh_interp": 0.9095750419011684,
        "u_interp": 42.46522120292294,
        "v_interp": 0.017080296452233856,
        "w_interp": 0.036629335325113845
    },
    {
        "point_1": [
            47.97224,
            3.177,
            18148.19922
        ],
        "point_2": [
            47.97439,
            3.18379,
            18248.0
        ],
        "gh_interp": 0.9532224218743827,
        "u_interp": 42.40817527744106,
        "v_interp": 0.07668838146819712,
        "w_interp": 0.03878693534152521
    },
    {
        "point_1": [
            47.97439,
            3.18379,
            18248.0
        ],
        "point_2": [
            47.97612,
            3.18997,
            18365.5
        ],
        "gh_interp": 0.99803803424538,
        "u_interp": 42.34960250433738,
        "v_interp": 0.13789189090890686,
        "w_interp": 0.04100228403018623
    },
    {
        "point_1": [
            47.97612,
            3.18997,
            18365.5
        ],
        "point_2": [
            47.97747,
            3.19673,
            18504.59961
        ],
        "gh_interp": 0.05396122110750788,
        "u_interp": 42.097408337852634,
        "v_interp": 0.2410588514529433,
        "w_interp": 0.04037767716450936
    },
    {
        "point_1": [
            47.97747,
            3.19673,
            18504.59961
        ],
        "point_2": [
            47.97775,
            3.20336,
            18658.1
        ],
        "gh_interp": 0.12030903153381911,
        "u_interp": 41.79047682274937,
        "v_interp": 0.36461293581741117,
        "w_interp": 0.039490446787831396
    },
    {
        "point_1": [
            47.97775,
            3.20336,
            18658.1
        ],
        "point_2": [
            47.97824,
            3.20992,
            18454.0
        ],
        "gh_interp": 0.19352573412618862,
        "u_interp": 41.45176913498777,
        "v_interp": 0.5009583945576497,
        "w_interp": 0.0385113627426647
    },
    {
        "point_1": [
            47.97824,
            3.20992,
            18454.0
        ],
        "point_2": [
            47.9801,
            3.21651,
            18192.2
        ],
        "gh_interp": 0.09617400101917331,
        "u_interp": 41.902127854416065,
        "v_interp": 0.31966824846171504,
        "w_interp": 0.0398131904032884
    },
    {
        "point_1": [
            47.9801,
            3.21651,
            18192.2
        ],
        "point_2": [
            47.98281,
            3.22293,
            17930.59961
        ],
        "gh_interp": 0.972981003926563,
        "u_interp": 42.3823513539875,
        "v_interp": 0.10367216009326063,
        "w_interp": 0.03976365185890178
    },
    {
        "point_1": [
            47.98281,
            3.22293,
            17930.59961
        ],
        "point_2": [
            47.98677,
            3.22905,
            17668.40039
        ],
        "gh_interp": 0.8555091597752296,
        "u_interp": 42.535883824247776,
        "v_interp": -0.05675606440616754,
        "w_interp": 0.033956722484805704
    },
    {
        "point_1": [
            47.98677,
            3.22905,
            17668.40039
        ],
        "point_2": [
            47.9897,
            3.2333,
            17420.5
        ],
        "gh_interp": 0.7377684105797047,
        "u_interp": 42.68976774600691,
        "v_interp": -0.21755152548990475,
        "w_interp": 0.028136500456531606
    },
    {
        "point_1": [
            47.9897,
            3.2333,
            17420.5
        ],
        "point_2": [
            47.9927,
            3.23602,
            17192.4
        ],
        "gh_interp": 0.626448561327436,
        "u_interp": 42.83525972809143,
        "v_interp": -0.36957813149158447,
        "w_interp": 0.022633679697965956
    },
    {
        "point_1": [
            47.9927,
            3.23602,
            17192.4
        ],
        "point_2": [
            47.9956,
            3.23952,
            16954.80078
        ],
        "gh_interp": 0.5240200915116264,
        "u_interp": 42.969130921732884,
        "v_interp": -0.5094620131949696,
        "w_interp": 0.01757038223793041
    },
    {
        "point_1": [
            47.9956,
            3.23952,
            16954.80078
        ],
        "point_2": [
            47.99804,
            3.24447,
            16727.6
        ],
        "gh_interp": 0.41732599009106497,
        "u_interp": 43.10857717859249,
        "v_interp": -0.6551713563922376,
        "w_interp": 0.01229622385506134
    },
    {
        "point_1": [
            47.99804,
            3.24447,
            16727.6
        ],
        "point_2": [
            48.00052,
            3.24967,
            16517.0
        ],
        "gh_interp": 0.3153013156659933,
        "u_interp": 43.241920622761135,
        "v_interp": -0.7945037852937609,
        "w_interp": 0.0072528870190590716
    },
    {
        "point_1": [
            48.00052,
            3.24967,
            16517.0
        ],
        "point_2": [
            48.0043,
            3.25527,
            16303.09961
        ],
        "gh_interp": 0.22073123349497406,
        "u_interp": 43.365521119827726,
        "v_interp": -0.9236556725657158,
        "w_interp": 0.0025780494693725953
    },
    {
        "point_1": [
            48.0043,
            3.25527,
            16303.09961
        ],
        "point_2": [
            48.00814,
            3.25956,
            16095.2
        ],
        "gh_interp": 0.12467910880972584,
        "u_interp": 43.49105860570967,
        "v_interp": -1.054831546529189,
        "w_interp": -0.0021700491776577594
    },
    {
        "point_1": [
            48.00814,
            3.25956,
            16095.2
        ],
        "point_2": [
            48.01124,
            3.26264,
            15898.59961
        ],
        "gh_interp": 0.03132163871939888,
        "u_interp": 43.61307425212919,
        "v_interp": -1.182327401204419,
        "w_interp": -0.006784944255498094
    },
    {
        "point_1": [
            48.01124,
            3.26264,
            15898.59961
        ],
        "point_2": [
            48.01408,
            3.2663,
            15698.5
        ],
        "gh_interp": 0.9500164120900452,
        "u_interp": 43.5928295752096,
        "v_interp": -1.6986450465285525,
        "w_interp": -0.006831335341268806
    },
    {
        "point_1": [
            48.01408,
            3.2663,
            15698.5
        ],
        "point_2": [
            48.01665,
            3.2705,
            15500.90039
        ],
        "gh_interp": 0.8711695276121094,
        "u_interp": 43.49631896016855,
        "v_interp": -2.4456372607101287,
        "w_interp": -0.004462128980128679
    },
    {
        "point_1": [
            48.01665,
            3.2705,
            15500.90039
        ],
        "point_2": [
            48.01932,
            3.27469,
            15307.0
        ],
        "gh_interp": 0.7933077385633694,
        "u_interp": 43.40101412727572,
        "v_interp": -3.183296720392814,
        "w_interp": -0.002122522956054928
    },
    {
        "point_1": [
            48.01932,
            3.27469,
            15307.0
        ],
        "point_2": [
            48.02319,
            3.27864,
            15113.7
        ],
        "gh_interp": 0.7169035834000645,
        "u_interp": 43.307493475758214,
        "v_interp": -3.907146615236548,
        "w_interp": 0.00017328380446576808
    },
    {
        "point_1": [
            48.02319,
            3.27864,
            15113.7
        ],
        "point_2": [
            48.02732,
            3.28249,
            14935.40039
        ],
        "gh_interp": 0.6407360048146542,
        "u_interp": 43.2142624000583,
        "v_interp": -4.628755193090841,
        "w_interp": 0.002461981866437934
    },
    {
        "point_1": [
            48.02732,
            3.28249,
            14935.40039
        ],
        "point_2": [
            48.03212,
            3.28522,
            14747.0
        ],
        "gh_interp": 0.5704791524793046,
        "u_interp": 43.12826620534968,
        "v_interp": -5.294365788042086,
        "w_interp": 0.004573073288359274
    },
    {
        "point_1": [
            48.03212,
            3.28522,
            14747.0
        ],
        "point_2": [
            48.03703,
            3.28837,
            14552.2998
        ],
        "gh_interp": 0.4962422072602303,
        "u_interp": 43.03739827455825,
        "v_interp": -5.997683622988259,
        "w_interp": 0.0068037593073339425
    },
    {
        "point_1": [
            48.03703,
            3.28837,
            14552.2998
        ],
        "point_2": [
            48.04121,
            3.29248,
            14367.6
        ],
        "gh_interp": 0.419522896426836,
        "u_interp": 42.94349186439276,
        "v_interp": -6.7245192899822905,
        "w_interp": 0.009109035926090244
    },
    {
        "point_1": [
            48.04121,
            3.29248,
            14367.6
        ],
        "point_2": [
            48.04392,
            3.29671,
            14191.5
        ],
        "gh_interp": 0.34674412492549267,
        "u_interp": 42.85440877574527,
        "v_interp": -7.4140224457400405,
        "w_interp": 0.011295906460527125
    },
    {
        "point_1": [
            48.04392,
            3.29671,
            14191.5
        ],
        "point_2": [
            48.04585,
            3.3022,
            14006.5
        ],
        "gh_interp": 0.2773540028929482,
        "u_interp": 42.76947348122506,
        "v_interp": -8.071421672641964,
        "w_interp": 0.01338095420348264
    },
    {
        "point_1": [
            48.04585,
            3.3022,
            14006.5
        ],
        "point_2": [
            48.04813,
            3.3092,
            13834.40039
        ],
        "gh_interp": 0.20445694113246723,
        "u_interp": 42.680245602257216,
        "v_interp": -8.76204550555994,
        "w_interp": 0.015571379146394447
    },
    {
        "point_1": [
            48.04813,
            3.3092,
            13834.40039
        ],
        "point_2": [
            48.0512,
            3.31629,
            13650.7002
        ],
        "gh_interp": 0.13664312546152327,
        "u_interp": 42.59723974727617,
        "v_interp": -9.40451086935393,
        "w_interp": 0.017609061732391164
    },
    {
        "point_1": [
            48.0512,
            3.31629,
            13650.7002
        ],
        "point_2": [
            48.0548,
            3.32407,
            13479.0
        ],
        "gh_interp": 0.06425823845697087,
        "u_interp": 42.50863878338595,
        "v_interp": -10.09028237922183,
        "w_interp": 0.01978409674965409
    },
    {
        "point_1": [
            48.0548,
            3.32407,
            13479.0
        ],
        "point_2": [
            48.05901,
            3.33134,
            13317.8
        ],
        "gh_interp": 0.9951915485380805,
        "u_interp": 42.51271369219654,
        "v_interp": -10.719808878288596,
        "w_interp": 0.021672769046716465
    },
    {
        "point_1": [
            48.05901,
            3.33134,
            13317.8
        ],
        "point_2": [
            48.06315,
            3.33895,
            13164.09961
        ],
        "gh_interp": 0.9053121110250802,
        "u_interp": 44.05907517894241,
        "v_interp": -11.107602441412181,
        "w_interp": 0.020884498320930492
    },
    {
        "point_1": [
            48.06315,
            3.33895,
            13164.09961
        ],
        "point_2": [
            48.0676,
            3.34717,
            13008.4
        ],
        "gh_interp": 0.819614191678128,
        "u_interp": 45.533494307936316,
        "v_interp": -11.477354438258239,
        "w_interp": 0.020132900814857992
    },
    {
        "point_1": [
            48.0676,
            3.34717,
            13008.4
        ],
        "point_2": [
            48.07241,
            3.35471,
            12849.7998
        ],
        "gh_interp": 0.732801577734,
        "u_interp": 47.02709158092236,
        "v_interp": -11.8519158932139,
        "w_interp": 0.01937152708918
    },
    {
        "point_1": [
            48.07241,
            3.35471,
            12849.7998
        ],
        "point_2": [
            48.07851,
            3.36252,
            12683.0
        ],
        "gh_interp": 0.6443716970550348,
        "u_interp": 48.54851367192849,
        "v_interp": -12.233455202581846,
        "w_interp": 0.01859596942935494
    },
    {
        "point_1": [
            48.07851,
            3.36252,
            12683.0
        ],
        "point_2": [
            48.08458,
            3.37029,
            12531.3
        ],
        "gh_interp": 0.5513700084614807,
        "u_interp": 50.14859299399371,
        "v_interp": -12.634720021256173,
        "w_interp": 0.017780315586880032
    },
    {
        "point_1": [
            48.08458,
            3.37029,
            12531.3
        ],
        "point_2": [
            48.09106,
            3.37823,
            12386.2998
        ],
        "gh_interp": 0.4667874360624599,
        "u_interp": 51.60382275540405,
        "v_interp": -12.999659745361932,
        "w_interp": 0.017038500021732808
    },
    {
        "point_1": [
            48.09106,
            3.37823,
            12386.2998
        ],
        "point_2": [
            48.09848,
            3.38607,
            12237.2002
        ],
        "gh_interp": 0.38405255334305743,
        "u_interp": 53.06907060953287,
        "v_interp": -12.902713695329046,
        "w_interp": 0.042897241336059454
    },
    {
        "point_1": [
            48.09848,
            3.38607,
            12237.2002
        ],
        "point_2": [
            48.10638,
            3.39375,
            12086.9
        ],
        "gh_interp": 0.30077313467028666,
        "u_interp": 54.42776118569565,
        "v_interp": -13.25203731539765,
        "w_interp": 0.046680599338773894
    },
    {
        "point_1": [
            48.10638,
            3.39375,
            12086.9
        ],
        "point_2": [
            48.11453,
            3.40203,
            11946.09961
        ],
        "gh_interp": 0.21682312217930055,
        "u_interp": 55.797392394199086,
        "v_interp": -13.60417380644816,
        "w_interp": 0.05049442220938907
    },
    {
        "point_1": [
            48.11453,
            3.40203,
            11946.09961
        ],
        "point_2": [
            48.12497,
            3.41115,
            11798.0
        ],
        "gh_interp": 0.13817921818425746,
        "u_interp": 57.080455279767136,
        "v_interp": -13.934053309423827,
        "w_interp": 0.054067190226820445
    },
    {
        "point_1": [
            48.12497,
            3.41115,
            11798.0
        ],
        "point_2": [
            48.13663,
            3.42038,
            11660.7998
        ],
        "gh_interp": 0.05545834283339206,
        "u_interp": 58.4300333097577,
        "v_interp": -14.281034065213564,
        "w_interp": 0.057825173780715826
    },
    {
        "point_1": [
            48.13663,
            3.42038,
            11660.7998
        ],
        "point_2": [
            48.15206,
            3.43078,
            11504.5
        ],
        "gh_interp": 0.9816175786820518,
        "u_interp": 57.99579415107043,
        "v_interp": -16.23779578663634,
        "w_interp": 0.02788985677465068
    },
    {
        "point_1": [
            48.15206,
            3.43078,
            11504.5
        ],
        "point_2": [
            48.16756,
            3.44042,
            11352.09961
        ],
        "gh_interp": 0.8684589524142832,
        "u_interp": 57.75550818993952,
        "v_interp": -17.001958393338324,
        "w_interp": 0.03493966136088637
    },
    {
        "point_1": [
            48.16756,
            3.44042,
            11352.09961
        ],
        "point_2": [
            48.18534,
            3.44992,
            11222.6
        ],
        "gh_interp": 0.7581234383888512,
        "u_interp": 57.52121694844161,
        "v_interp": -17.747056463104244,
        "w_interp": 0.04181358550132743
    },
    {
        "point_1": [
            48.18534,
            3.44992,
            11222.6
        ],
        "point_2": [
            48.20396,
            3.45927,
            11103.4
        ],
        "gh_interp": 0.6643677332004145,
        "u_interp": 57.322131995966124,
        "v_interp": -18.380190731634908,
        "w_interp": 0.04765458430294921
    },
    {
        "point_1": [
            48.20396,
            3.45927,
            11103.4
        ],
        "point_2": [
            48.22341,
            3.46807,
            11000.3
        ],
        "gh_interp": 0.5780687855938402,
        "u_interp": 57.13888104768082,
        "v_interp": -18.962969357831977,
        "w_interp": 0.05303102564631174
    },
    {
        "point_1": [
            48.22341,
            3.46807,
            11000.3
        ],
        "point_2": [
            48.24176,
            3.47553,
            10888.90039
        ],
        "gh_interp": 0.5034259877898318,
        "u_interp": 56.98038127613538,
        "v_interp": -19.467033756832965,
        "w_interp": 0.057681286573330846
    },
    {
        "point_1": [
            48.24176,
            3.47553,
            10888.90039
        ],
        "point_2": [
            48.26058,
            3.48275,
            10763.5
        ],
        "gh_interp": 0.4227744013235346,
        "u_interp": 56.80912218074014,
        "v_interp": -20.01167563329847,
        "w_interp": 0.06270589621123732
    },
    {
        "point_1": [
            48.26058,
            3.48275,
            10763.5
        ],
        "point_2": [
            48.27859,
            3.48973,
            10643.2998
        ],
        "gh_interp": 0.3319864677123434,
        "u_interp": 56.61633912383705,
        "v_interp": -20.624768477331834,
        "w_interp": 0.06836200226215834
    },
    {
        "point_1": [
            48.27859,
            3.48973,
            10643.2998
        ],
        "point_2": [
            48.29673,
            3.49724,
            10522.5
        ],
        "gh_interp": 0.24496339084909144,
        "u_interp": 56.43155052791353,
        "v_interp": -21.212437163779924,
        "w_interp": 0.07378355700008149
    },
    {
        "point_1": [
            48.29673,
            3.49724,
            10522.5
        ],
        "point_2": [
            48.31497,
            3.50461,
            10402.2
        ],
        "gh_interp": 0.15750621290375036,
        "u_interp": 56.24584014282397,
        "v_interp": -21.803037344055767,
        "w_interp": 0.07923215632046676
    },
    {
        "point_1": [
            48.31497,
            3.50461,
            10402.2
        ],
        "point_2": [
            48.33197,
            3.51087,
            10286.6
        ],
        "gh_interp": 0.07041088239141169,
        "u_interp": 56.06089812035147,
        "v_interp": -22.391193960930824,
        "w_interp": 0.08465821247488377
    },
    {
        "point_1": [
            48.33197,
            3.51087,
            10286.6
        ],
        "point_2": [
            48.34877,
            3.51632,
            10167.2998
        ],
        "gh_interp": 0.9844327434787007,
        "u_interp": 55.73765602118581,
        "v_interp": -22.953739176974846,
        "w_interp": 0.08976883083740624
    },
    {
        "point_1": [
            48.34877,
            3.51632,
            10167.2998
        ],
        "point_2": [
            48.36688,
            3.5218,
            10035.8
        ],
        "gh_interp": 0.8831983373358597,
        "u_interp": 54.60789319415167,
        "v_interp": -23.519887063250955,
        "w_interp": 0.09447707069773434
    },
    {
        "point_1": [
            48.36688,
            3.5218,
            10035.8
        ],
        "point_2": [
            48.38387,
            3.52674,
            9915.8
        ],
        "gh_interp": 0.7716117334500109,
        "u_interp": 53.362601184562195,
        "v_interp": -24.143929049900873,
        "w_interp": 0.09966677364865296
    },
    {
        "point_1": [
            48.38387,
            3.52674,
            9915.8
        ],
        "point_2": [
            48.4007,
            3.53185,
            9800.2998
        ],
        "gh_interp": 0.6800261262164806,
        "u_interp": 52.62041319557136,
        "v_interp": -25.78417183245815,
        "w_interp": 0.1148371776884805
    },
    {
        "point_1": [
            48.4007,
            3.53185,
            9800.2998
        ],
        "point_2": [
            48.41806,
            3.53703,
            9682.6
        ],
        "gh_interp": 0.5819929654830579,
        "u_interp": 51.91850849455095,
        "v_interp": -26.12654706673452,
        "w_interp": 0.12347471366871818
    },
    {
        "point_1": [
            48.41806,
            3.53703,
            9682.6
        ],
        "point_2": [
            48.43488,
            3.54166,
            9546.7
        ],
        "gh_interp": 0.4820928491915547,
        "u_interp": 51.203236634163154,
        "v_interp": -26.475442537039186,
        "w_interp": 0.13227674394543454
    },
    {
        "point_1": [
            48.43488,
            3.54166,
            9546.7
        ],
        "point_2": [
            48.45243,
            3.54612,
            9336.5
        ],
        "gh_interp": 0.3667449403249703,
        "u_interp": 50.37736058486909,
        "v_interp": -26.878288543696833,
        "w_interp": 0.1424398530977504
    },
    {
        "point_1": [
            48.45243,
            3.54612,
            9336.5
        ],
        "point_2": [
            48.46815,
            3.55044,
            9116.2998
        ],
        "gh_interp": 0.1883333844474413,
        "u_interp": 49.09995701193595,
        "v_interp": -27.50138074825487,
        "w_interp": 0.1581593935231868
    },
    {
        "point_1": [
            48.46815,
            3.55044,
            9116.2998
        ],
        "point_2": [
            48.48289,
            3.55483,
            8900.0
        ],
        "gh_interp": 0.0014339539691215833,
        "u_interp": 47.76178135903115,
        "v_interp": -28.15411637176639,
        "w_interp": 0.17462678622342065
    },
    {
        "point_1": [
            48.48289,
            3.55483,
            8900.0
        ],
        "point_2": [
            48.49737,
            3.55978,
            8684.59961
        ],
        "gh_interp": 0.7945060350018889,
        "u_interp": 47.29251122945788,
        "v_interp": -28.86439752884966,
        "w_interp": 0.15018251194276683
    },
    {
        "point_1": [
            48.49737,
            3.55978,
            8684.59961
        ],
        "point_2": [
            48.51131,
            3.56468,
            8544.2
        ],
        "gh_interp": 0.588255591437665,
        "u_interp": 46.831818309823646,
        "v_interp": -29.572266983520283,
        "w_interp": 0.1255214433502373
    },
    {
        "point_1": [
            48.51131,
            3.56468,
            8544.2
        ],
        "point_2": [
            48.52505,
            3.56983,
            8419.2998
        ],
        "gh_interp": 0.45381998601121415,
        "u_interp": 46.531535166202566,
        "v_interp": -30.033661669791126,
        "w_interp": 0.10944717156004072
    },
    {
        "point_1": [
            48.52505,
            3.56983,
            8419.2998
        ],
        "point_2": [
            48.53837,
            3.57549,
            8291.0
        ],
        "gh_interp": 0.33422539450996297,
        "u_interp": 46.264401769643264,
        "v_interp": -30.444120705924956,
        "w_interp": 0.0951474184378637
    },
    {
        "point_1": [
            48.53837,
            3.57549,
            8291.0
        ],
        "point_2": [
            48.55084,
            3.58133,
            8182.3
        ],
        "gh_interp": 0.21137561387956927,
        "u_interp": 45.98999739437501,
        "v_interp": -30.865751834171057,
        "w_interp": 0.08045844703810057
    },
    {
        "point_1": [
            48.55084,
            3.58133,
            8182.3
        ],
        "point_2": [
            48.56361,
            3.58802,
            8068.6
        ],
        "gh_interp": 0.10729305759714557,
        "u_interp": 45.757512576848725,
        "v_interp": -31.222972216746484,
        "w_interp": 0.06801344563393438
    },
    {
        "point_1": [
            48.56361,
            3.58802,
            8068.6
        ],
        "point_2": [
            48.57504,
            3.59464,
            7966.9
        ],
        "gh_interp": 0.9982456514446647,
        "u_interp": 45.52384863005391,
        "v_interp": -31.573615332255116,
        "w_interp": 0.055038083334531335
    },
    {
        "point_1": [
            48.57504,
            3.59464,
            7966.9
        ],
        "point_2": [
            48.58678,
            3.60167,
            7864.7
        ],
        "gh_interp": 0.8899216492915147,
        "u_interp": 45.893832634615706,
        "v_interp": -30.48713357413269,
        "w_interp": 0.045993166791991044
    },
    {
        "point_1": [
            48.58678,
            3.60167,
            7864.7
        ],
        "point_2": [
            48.59861,
            3.60833,
            7763.2
        ],
        "gh_interp": 0.7810650807560985,
        "u_interp": 46.265635636250074,
        "v_interp": -29.39531021444625,
        "w_interp": 0.03690378163321416
    },
    {
        "point_1": [
            48.59861,
            3.60833,
            7763.2
        ],
        "point_2": [
            48.61029,
            3.61441,
            7669.2002
        ],
        "gh_interp": 0.6729541051558561,
        "u_interp": 46.63489204198283,
        "v_interp": -28.310965096949445,
        "w_interp": 0.027876652537168596
    },
    {
        "point_1": [
            48.61029,
            3.61441,
            7669.2002
        ],
        "point_2": [
            48.62184,
            3.62013,
            7576.6001
        ],
        "gh_interp": 0.5728318383161751,
        "u_interp": 46.976862764028134,
        "v_interp": -27.30674613955362,
        "w_interp": 0.019516570472119736
    },
    {
        "point_1": [
            48.62184,
            3.62013,
            7576.6001
        ],
        "point_2": [
            48.63411,
            3.62627,
            7479.2998
        ],
        "gh_interp": 0.47420043780701193,
        "u_interp": 47.31374138566847,
        "v_interp": -26.317480461576118,
        "w_interp": 0.011280973851363743
    },
    {
        "point_1": [
            48.63411,
            3.62627,
            7479.2998
        ],
        "point_2": [
            48.64531,
            3.6325,
            7393.1
        ],
        "gh_interp": 0.377794501060133,
        "u_interp": 48.30576093685172,
        "v_interp": -23.031384628772628,
        "w_interp": 0.06969661272513698
    },
    {
        "point_1": [
            48.64531,
            3.6325,
            7393.1
        ],
        "point_2": [
            48.65578,
            3.63863,
            7310.8999
        ],
        "gh_interp": 0.2858274509395337,
        "u_interp": 48.20050738724165,
        "v_interp": -22.327843571548552,
        "w_interp": 0.06891500907067327
    },
    {
        "point_1": [
            48.65578,
            3.63863,
            7310.8999
        ],
        "point_2": [
            48.66658,
            3.64475,
            7227.1
        ],
        "gh_interp": 0.19812770318352585,
        "u_interp": 48.10013763808559,
        "v_interp": -21.65694705835566,
        "w_interp": 0.06816967209126866
    },
    {
        "point_1": [
            48.66658,
            3.64475,
            7227.1
        ],
        "point_2": [
            48.6767,
            3.65025,
            7148.0
        ],
        "gh_interp": 0.10872111983412991,
        "u_interp": 47.99781446643126,
        "v_interp": -20.972993380490138,
        "w_interp": 0.0674098291672283
    },
    {
        "point_1": [
            48.6767,
            3.65025,
            7148.0
        ],
        "point_2": [
            48.68674,
            3.65607,
            7067.2998
        ],
        "gh_interp": 0.024328886156795532,
        "u_interp": 47.90123006862342,
        "v_interp": -20.327399102702664,
        "w_interp": 0.06669260187588796
    },
    {
        "point_1": [
            48.68674,
            3.65607,
            7067.2998
        ],
        "point_2": [
            48.69688,
            3.66301,
            6982.7
        ],
        "gh_interp": 0.9312771623642325,
        "u_interp": 46.876246961560945,
        "v_interp": -19.713293287796578,
        "w_interp": 0.06680637143371164
    },
    {
        "point_1": [
            48.69688,
            3.66301,
            6982.7
        ],
        "point_2": [
            48.70633,
            3.66978,
            6902.2002
        ],
        "gh_interp": 0.8308584775527708,
        "u_interp": 45.41921415085312,
        "v_interp": -19.087906435813924,
        "w_interp": 0.06727474027791439
    },
    {
        "point_1": [
            48.70633,
            3.66978,
            6902.2002
        ],
        "point_2": [
            48.71601,
            3.67724,
            6817.0
        ],
        "gh_interp": 0.7353064308152409,
        "u_interp": 44.03279420830696,
        "v_interp": -18.49282800173686,
        "w_interp": 0.0677204103419636
    },
    {
        "point_1": [
            48.71601,
            3.67724,
            6817.0
        ],
        "point_2": [
            48.72495,
            3.68458,
            6738.4
        ],
        "gh_interp": 0.634175080272172,
        "u_interp": 42.56542091807614,
        "v_interp": -17.863002814605302,
        "w_interp": 0.06819210317338688
    },
    {
        "point_1": [
            48.72495,
            3.68458,
            6738.4
        ],
        "point_2": [
            48.73319,
            3.6913,
            6662.2998
        ],
        "gh_interp": 0.5408780674402156,
        "u_interp": 41.211720567464965,
        "v_interp": -17.28196826646409,
        "w_interp": 0.06862725539779327
    },
    {
        "point_1": [
            48.73319,
            3.6913,
            6662.2998
        ],
        "point_2": [
            48.74157,
            3.69803,
            6573.7998
        ],
        "gh_interp": 0.4505482794514829,
        "u_interp": 39.90107339925149,
        "v_interp": -16.719412982488834,
        "w_interp": 0.06904856800985142
    },
    {
        "point_1": [
            48.74157,
            3.69803,
            6573.7998
        ],
        "point_2": [
            48.74945,
            3.70432,
            6483.0
        ],
        "gh_interp": 0.3455001161483265,
        "u_interp": 38.37686880600608,
        "v_interp": -16.065194693551213,
        "w_interp": 0.06953852948389677
    },
    {
        "point_1": [
            48.74945,
            3.70432,
            6483.0
        ],
        "point_2": [
            48.75665,
            3.71063,
            6386.1
        ],
        "gh_interp": 0.23772212498116357,
        "u_interp": 36.81305556051723,
        "v_interp": -15.393975599857681,
        "w_interp": 0.0700412233127219
    },
    {
        "point_1": [
            48.75665,
            3.71063,
            6386.1
        ],
        "point_2": [
            48.76336,
            3.71666,
            6289.7998
        ],
        "gh_interp": 0.12270328855092834,
        "u_interp": 35.14418070079431,
        "v_interp": -14.677662015698868,
        "w_interp": 0.07057768960464275
    },
    {
        "point_1": [
            48.76336,
            3.71666,
            6289.7998
        ],
        "point_2": [
            48.77205,
            3.7247,
            6155.5
        ],
        "gh_interp": 0.008396405661361291,
        "u_interp": 33.48563598700389,
        "v_interp": -13.965782331310724,
        "w_interp": 0.07111083523111578
    },
    {
        "point_1": [
            48.77205,
            3.7247,
            6155.5
        ],
        "point_2": [
            48.7778,
            3.73018,
            6066.3
        ],
        "gh_interp": 0.8345760073341468,
        "u_interp": 32.588982202931334,
        "v_interp": -14.34589652478969,
        "w_interp": 0.06097002503740024
    },
    {
        "point_1": [
            48.7778,
            3.73018,
            6066.3
        ],
        "point_2": [
            48.78411,
            3.7362,
            5974.0
        ],
        "gh_interp": 0.7185949064756608,
        "u_interp": 32.04574110380608,
        "v_interp": -14.64906197911777,
        "w_interp": 0.05383270242885745
    },
    {
        "point_1": [
            48.78411,
            3.7362,
            5974.0
        ],
        "point_2": [
            48.7899,
            3.74147,
            5896.8
        ],
        "gh_interp": 0.5985830722913749,
        "u_interp": 31.483620549442158,
        "v_interp": -14.962763452598507,
        "w_interp": 0.04644733385521953
    },
    {
        "point_1": [
            48.7899,
            3.74147,
            5896.8
        ],
        "point_2": [
            48.79835,
            3.74914,
            5781.6
        ],
        "gh_interp": 0.49820481011340273,
        "u_interp": 31.01346121253106,
        "v_interp": -15.225144316658234,
        "w_interp": 0.04027018917607712
    },
    {
        "point_1": [
            48.79835,
            3.74914,
            5781.6
        ],
        "point_2": [
            48.80673,
            3.75744,
            5666.7002
        ],
        "gh_interp": 0.34841755878047,
        "u_interp": 30.311876295275116,
        "v_interp": -15.61667638323441,
        "w_interp": 0.031052481053833507
    },
    {
        "point_1": [
            48.80673,
            3.75744,
            5666.7002
        ],
        "point_2": [
            48.81374,
            3.76546,
            5565.0
        ],
        "gh_interp": 0.19902063846186108,
        "u_interp": 29.6121196401039,
        "v_interp": -16.007188155310704,
        "w_interp": 0.02185879338279037
    },
    {
        "point_1": [
            48.81374,
            3.76546,
            5565.0
        ],
        "point_2": [
            48.81882,
            3.77131,
            5491.7
        ],
        "gh_interp": 0.06678632059719458,
        "u_interp": 28.992750487309515,
        "v_interp": -16.352838237578155,
        "w_interp": 0.013721269428156664
    },
    {
        "point_1": [
            48.81882,
            3.77131,
            5491.7
        ],
        "point_2": [
            48.82402,
            3.77726,
            5410.8
        ],
        "gh_interp": 0.9692471881653075,
        "u_interp": 28.76794834336421,
        "v_interp": -16.548854999833537,
        "w_interp": 0.01055222300946437
    },
    {
        "point_1": [
            48.82402,
            3.77726,
            5410.8
        ],
        "point_2": [
            48.82893,
            3.78288,
            5335.0
        ],
        "gh_interp": 0.8558269155730805,
        "u_interp": 29.092565112426243,
        "v_interp": -16.627937975430218,
        "w_interp": 0.01402236271588126
    },
    {
        "point_1": [
            48.82893,
            3.78288,
            5335.0
        ],
        "point_2": [
            48.83397,
            3.78878,
            5255.7002
        ],
        "gh_interp": 0.7495567466918586,
        "u_interp": 29.396717783562238,
        "v_interp": -16.702035497682733,
        "w_interp": 0.017273742069977702
    },
    {
        "point_1": [
            48.83397,
            3.78878,
            5255.7002
        ],
        "point_2": [
            48.83938,
            3.79546,
            5167.4
        ],
        "gh_interp": 0.6383799242875433,
        "u_interp": 29.71491364095736,
        "v_interp": -16.77955421397719,
        "w_interp": 0.02067524249879005
    },
    {
        "point_1": [
            48.83938,
            3.79546,
            5167.4
        ],
        "point_2": [
            48.84401,
            3.80143,
            5089.6001
        ],
        "gh_interp": 0.5145847110125338,
        "u_interp": 30.069224217366894,
        "v_interp": -16.865871180130245,
        "w_interp": 0.024462807765842663
    },
    {
        "point_1": [
            48.84401,
            3.80143,
            5089.6001
        ],
        "point_2": [
            48.84854,
            3.80784,
            4997.0
        ],
        "gh_interp": 0.4055107200898139,
        "u_interp": 30.381401623687648,
        "v_interp": -16.94192368437158,
        "w_interp": 0.02779997120397943
    },
    {
        "point_1": [
            48.84854,
            3.80784,
            4997.0
        ],
        "point_2": [
            48.85261,
            3.81356,
            4907.0
        ],
        "gh_interp": 0.275687128197756,
        "u_interp": 30.75296584218976,
        "v_interp": -17.03244397421769,
        "w_interp": 0.0317719771845502
    },
    {
        "point_1": [
            48.85261,
            3.81356,
            4907.0
        ],
        "point_2": [
            48.85658,
            3.81963,
            4816.6
        ],
        "gh_interp": 0.1495088274153027,
        "u_interp": 31.114096982060996,
        "v_interp": -17.12042256264416,
        "w_interp": 0.0356324539902056
    },
    {
        "point_1": [
            48.85658,
            3.81963,
            4816.6
        ],
        "point_2": [
            48.86036,
            3.82608,
            4732.3999
        ],
        "gh_interp": 0.022769734184927844,
        "u_interp": 31.476833149220543,
        "v_interp": -17.208792167019187,
        "w_interp": 0.03951008847055278
    },
    {
        "point_1": [
            48.86036,
            3.82608,
            4732.3999
        ],
        "point_2": [
            48.86388,
            3.83228,
            4655.2002
        ],
        "gh_interp": 0.8976705645176118,
        "u_interp": 31.479127698215503,
        "v_interp": -16.815270737935432,
        "w_interp": 0.03906571460947951
    },
    {
        "point_1": [
            48.86388,
            3.83228,
            4655.2002
        ],
        "point_2": [
            48.86737,
            3.83843,
            4562.3
        ],
        "gh_interp": 0.7814268990094237,
        "u_interp": 31.407704385692977,
        "v_interp": -16.35020517185212,
        "w_interp": 0.037769540938928245
    },
    {
        "point_1": [
            48.86737,
            3.83843,
            4562.3
        ],
        "point_2": [
            48.87073,
            3.845,
            4437.0
        ],
        "gh_interp": 0.6415421614464053,
        "u_interp": 31.321755346797676,
        "v_interp": -15.79055682992524,
        "w_interp": 0.03620975776323006
    },
    {
        "point_1": [
            48.87073,
            3.845,
            4437.0
        ],
        "point_2": [
            48.87397,
            3.85097,
            4324.3999
        ],
        "gh_interp": 0.45287133386318973,
        "u_interp": 31.20583078933084,
        "v_interp": -15.035725976563912,
        "w_interp": 0.03410598584546258
    },
    {
        "point_1": [
            48.87397,
            3.85097,
            4324.3999
        ],
        "point_2": [
            48.87722,
            3.85658,
            4230.6
        ],
        "gh_interp": 0.2833234164413802,
        "u_interp": 31.10165587501941,
        "v_interp": -14.357401718211392,
        "w_interp": 0.032215443720021164
    },
    {
        "point_1": [
            48.87722,
            3.85658,
            4230.6
        ],
        "point_2": [
            48.88043,
            3.8625,
            4123.8999
        ],
        "gh_interp": 0.15542143499354794,
        "u_interp": 31.418308582624555,
        "v_interp": -12.75158573740187,
        "w_interp": 0.028964570958543257
    },
    {
        "point_1": [
            48.88043,
            3.8625,
            4123.8999
        ],
        "point_2": [
            48.88635,
            3.87232,
            3935.7
        ],
        "gh_interp": 0.9942677222279517,
        "u_interp": 30.93318606874551,
        "v_interp": -12.015276602841173,
        "w_interp": 0.0242853693239228
    },
    {
        "point_1": [
            48.88635,
            3.87232,
            3935.7
        ],
        "point_2": [
            48.8912,
            3.88056,
            3784.2
        ],
        "gh_interp": 0.6908607148732906,
        "u_interp": 29.64239957624818,
        "v_interp": -12.618114060293724,
        "w_interp": 0.020533700324955342
    },
    {
        "point_1": [
            48.8912,
            3.88056,
            3784.2
        ],
        "point_2": [
            48.89493,
            3.88904,
            3620.4
        ],
        "gh_interp": 0.4416754772474457,
        "u_interp": 27.233116947824612,
        "v_interp": -11.580148468825954,
        "w_interp": 0.026316277665072614
    },
    {
        "point_1": [
            48.89493,
            3.88904,
            3620.4
        ],
        "point_2": [
            48.89806,
            3.89713,
            3459.7
        ],
        "gh_interp": 0.17758446545688156,
        "u_interp": 26.294456672076397,
        "v_interp": -11.706091987804061,
        "w_interp": 0.034433078520956034
    },
    {
        "point_1": [
            48.89806,
            3.89713,
            3459.7
        ],
        "point_2": [
            48.90023,
            3.90289,
            3338.69995
        ],
        "gh_interp": 0.9132096649603898,
        "u_interp": 25.798465006486005,
        "v_interp": -11.69469275031932,
        "w_interp": 0.041554800325210785
    },
    {
        "point_1": [
            48.90023,
            3.90289,
            3338.69995
        ],
        "point_2": [
            48.90229,
            3.90871,
            3211.0
        ],
        "gh_interp": 0.705482254766237,
        "u_interp": 26.1220529217293,
        "v_interp": -11.464711294043472,
        "w_interp": 0.04553673613920755
    },
    {
        "point_1": [
            48.90229,
            3.90871,
            3211.0
        ],
        "point_2": [
            48.90433,
            3.91453,
            3092.3
        ],
        "gh_interp": 0.48625275944435153,
        "u_interp": 26.463558240092173,
        "v_interp": -11.221995522708227,
        "w_interp": 0.04973915592622911
    },
    {
        "point_1": [
            48.90433,
            3.91453,
            3092.3
        ],
        "point_2": [
            48.90654,
            3.92064,
            2971.69995
        ],
        "gh_interp": 0.28247397100545446,
        "u_interp": 26.780995179493264,
        "v_interp": -10.996385708002007,
        "w_interp": 0.053645400437048865
    },
    {
        "point_1": [
            48.90654,
            3.92064,
            2971.69995
        ],
        "point_2": [
            48.90894,
            3.92656,
            2851.6
        ],
        "gh_interp": 0.07543326270999993,
        "u_interp": 27.103513383062083,
        "v_interp": -10.767164520688942,
        "w_interp": 0.05761417283230657
    },
    {
        "point_1": [
            48.90894,
            3.92656,
            2851.6
        ],
        "point_2": [
            48.91105,
            3.93157,
            2731.8
        ],
        "gh_interp": 0.8611065672124241,
        "u_interp": 27.352441954608643,
        "v_interp": -10.757570406807233,
        "w_interp": 0.05483026799774242
    },
    {
        "point_1": [
            48.91105,
            3.93157,
            2731.8
        ],
        "point_2": [
            48.9133,
            3.93631,
            2620.3
        ],
        "gh_interp": 0.6426280425878824,
        "u_interp": 27.559168290833945,
        "v_interp": -10.873846730515787,
        "w_interp": 0.0481766793653048
    },
    {
        "point_1": [
            48.9133,
            3.93631,
            2620.3
        ],
        "point_2": [
            48.91586,
            3.94107,
            2508.5
        ],
        "gh_interp": 0.4392861770149572,
        "u_interp": 27.75157218473312,
        "v_interp": -10.982067182047539,
        "w_interp": 0.041984065571341565
    },
    {
        "point_1": [
            48.91586,
            3.94107,
            2508.5
        ],
        "point_2": [
            48.91854,
            3.94594,
            2388.9
        ],
        "gh_interp": 0.2353972032835394,
        "u_interp": 27.94449375727059,
        "v_interp": -11.090578809682066,
        "w_interp": 0.035774790036228646
    },
    {
        "point_1": [
            48.91854,
            3.94594,
            2388.9
        ],
        "point_2": [
            48.92182,
            3.95205,
            2216.5
        ],
        "gh_interp": 0.01728341743132558,
        "u_interp": 28.150874974403692,
        "v_interp": -11.20666101598877,
        "w_interp": 0.029132309231224136
    },
    {
        "point_1": [
            48.92182,
            3.95205,
            2216.5
        ],
        "point_2": [
            48.92516,
            3.95872,
            2021.2
        ],
        "gh_interp": 0.6854448752433703,
        "u_interp": 27.51890512883756,
        "v_interp": -12.206173666158392,
        "w_interp": 0.006504281317315043
    },
    {
        "point_1": [
            48.92516,
            3.95872,
            2021.2
        ],
        "point_2": [
            48.9293,
            3.96689,
            1783.3
        ],
        "gh_interp": 0.3083791949179607,
        "u_interp": 26.741742244774528,
        "v_interp": -13.39328997156467,
        "w_interp": -0.019989590710021318
    },
    {
        "point_1": [
            48.9293,
            3.96689,
            1783.3
        ],
        "point_2": [
            48.93389,
            3.97586,
            1568.4
        ],
        "gh_interp": 0.8402334763143332,
        "u_interp": 25.396979038388665,
        "v_interp": -14.84649705254628,
        "w_interp": -0.044749274878745235
    },
    {
        "point_1": [
            48.93389,
            3.97586,
            1568.4
        ],
        "point_2": [
            48.93892,
            3.98503,
            1357.3
        ],
        "gh_interp": 0.4010469362532926,
        "u_interp": 23.447525844666792,
        "v_interp": -16.172405010013964,
        "w_interp": -0.05324882028103214
    },
    {
        "point_1": [
            48.93892,
            3.98503,
            1357.3
        ],
        "point_2": [
            48.94412,
            3.99372,
            1123.7
        ],
        "gh_interp": 0.9681297328765706,
        "u_interp": 21.593603910069046,
        "v_interp": -17.329662919662383,
        "w_interp": -0.05990971855344806
    },
    {
        "point_1": [
            48.94412,
            3.99372,
            1123.7
        ],
        "point_2": [
            48.94953,
            4.00221,
            859.6
        ],
        "gh_interp": 0.4672026394298338,
        "u_interp": 20.43423354412929,
        "v_interp": -16.488668005496464,
        "w_interp": -0.042611860292675746
    },
    {
        "point_1": [
            48.94953,
            4.00221,
            859.6
        ],
        "point_2": [
            48.95479,
            4.0126,
            564.9
        ],
        "gh_interp": 0.79489360964603,
        "u_interp": 19.43939394511058,
        "v_interp": -15.759752096993505,
        "w_interp": -0.02520494169077675
    },
    {
        "point_1": [
            48.95479,
            4.0126,
            564.9
        ],
        "point_2": [
            48.95957,
            4.02077,
            319.9
        ],
        "gh_interp": 0.4748137480889325,
        "u_interp": 19.702428708019124,
        "v_interp": -16.689148554090114,
        "w_interp": -0.016579201173429235
    },
    {
        "point_1": [
            48.95957,
            4.02077,
            319.9
        ],
        "point_2": [
            48.96258,
            4.02516,
            159.8
        ],
        "gh_interp": 0.3420034861103549,
        "u_interp": 13.875874300787743,
        "v_interp": -19.63516039475231,
        "w_interp": -0.009602449991712282
    },
    {
        "point_1": [
            48.96258,
            4.02516,
            159.8
        ],
        "point_2": [
            48.96259,
            4.02516,
            157.0
        ],
        "gh_interp": 0.5790014354769952,
        "u_interp": 8.697716713519096,
        "v_interp": -18.952410031656015,
        "w_interp": -0.004944829881536009
    },
    {
        "point_1": [
            48.96259,
            4.02516,
            157.0
        ],
        "point_2": [
            48.96258,
            4.02516,
            153.7
        ],
        "gh_interp": 0.5654605329425109,
        "u_interp": 8.627483761016759,
        "v_interp": -18.891998429123383,
        "w_interp": -0.004855889687491281
    },
    {
        "point_1": [
            48.96258,
            4.02516,
            153.7
        ],
        "point_2": [
            48.96258,
            4.02516,
            154.4
        ],
        "gh_interp": 0.5495016120982972,
        "u_interp": 8.544709209853291,
        "v_interp": -18.82079904042421,
        "w_interp": -0.004751067315938568
    },
    {
        "point_1": [
            48.96258,
            4.02516,
            154.4
        ],
        "point_2": [
            48.96257,
            4.02514,
            151.9
        ],
        "gh_interp": 0.5528868377319184,
        "u_interp": 8.562267447978876,
        "v_interp": -18.83590194105737,
        "w_interp": -0.00477330236444975
    },
    {
        "point_1": [
            48.96257,
            4.02514,
            151.9
        ],
        "point_2": [
            48.96257,
            4.02514,
            152.2
        ],
        "gh_interp": 0.5407967461832717,
        "u_interp": 8.499559454673218,
        "v_interp": -18.78196301022466,
        "w_interp": -0.004693891476909816
    },
    {
        "point_1": [
            48.96257,
            4.02514,
            152.2
        ],
        "point_2": [
            48.96257,
            4.02516,
            156.1
        ],
        "gh_interp": 0.5422475571691091,
        "u_interp": 8.507084413869896,
        "v_interp": -18.788435681924586,
        "w_interp": -0.004703420783414607
    },
    {
        "point_1": [
            48.96257,
            4.02516,
            156.1
        ],
        "point_2": [
            48.96258,
            4.02518,
            157.6
        ],
        "gh_interp": 0.561108099984998,
        "u_interp": 8.604908883426722,
        "v_interp": -18.87258041402361,
        "w_interp": -0.004827301767976905
    },
    {
        "point_1": [
            48.96258,
            4.02518,
            157.6
        ],
        "point_2": [
            48.96258,
            4.02518,
            156.9
        ],
        "gh_interp": 0.5683621549141861,
        "u_interp": 8.642533679410118,
        "v_interp": -18.904943772523232,
        "w_interp": -0.004874948300500866
    },
    {
        "point_1": [
            48.96258,
            4.02518,
            156.9
        ],
        "point_2": [
            48.96258,
            4.02517,
            156.4
        ],
        "gh_interp": 0.5649769292805651,
        "u_interp": 8.624975441284533,
        "v_interp": -18.889840871890076,
        "w_interp": -0.004852713251989684
    },
    {
        "point_1": [
            48.96258,
            4.02517,
            156.4
        ],
        "point_2": [
            48.96259,
            4.02517,
            160.0
        ],
        "gh_interp": 0.5625589109708357,
        "u_interp": 8.612433842623402,
        "v_interp": -18.879053085723534,
        "w_interp": -0.0048368310744816975
    },
    {
        "point_1": [
            48.96259,
            4.02517,
            160.0
        ],
        "point_2": [
            48.96258,
            4.02517,
            161.4
        ],
        "gh_interp": 0.579968642800887,
        "u_interp": 8.70273335298355,
        "v_interp": -18.956725146122633,
        "w_interp": -0.004951182752539203
    },
    {
        "point_1": [
            48.96258,
            4.02517,
            161.4
        ],
        "point_2": [
            48.96258,
            4.02517,
            156.0
        ],
        "gh_interp": 0.5867390940681292,
        "u_interp": 8.737849829234719,
        "v_interp": -18.98693094738895,
        "w_interp": -0.004995652849561567
    },
    {
        "point_1": [
            48.96258,
            4.02517,
            156.0
        ],
        "point_2": [
            48.96258,
            4.02516,
            158.8
        ],
        "gh_interp": 0.5606244963230522,
        "u_interp": 8.602400563694497,
        "v_interp": -18.8704228567903,
        "w_interp": -0.004824125332475308
    },
    {
        "point_1": [
            48.96258,
            4.02516,
            158.8
        ],
        "point_2": [
            48.96258,
            4.02516,
            161.1
        ],
        "gh_interp": 0.5741653988575366,
        "u_interp": 8.672633516196834,
        "v_interp": -18.93083445932293,
        "w_interp": -0.004913065526520035
    },
    {
        "point_1": [
            48.96258,
            4.02516,
            161.1
        ],
        "point_2": [
            48.96258,
            4.02518,
            160.6
        ],
        "gh_interp": 0.5852882830822915,
        "u_interp": 8.73032487003804,
        "v_interp": -18.980458275689024,
        "w_interp": -0.004986123543056774
    },
    {
        "point_1": [
            48.96258,
            4.02518,
            160.6
        ],
        "point_2": [
            48.96259,
            4.02518,
            160.0
        ],
        "gh_interp": 0.5828702647725621,
        "u_interp": 8.717783271376906,
        "v_interp": -18.969670489522482,
        "w_interp": -0.004970241365548787
    },
    {
        "point_1": [
            48.96259,
            4.02518,
            160.0
        ],
        "point_2": [
            48.96259,
            4.02518,
            158.8
        ],
        "gh_interp": 0.579968642800887,
        "u_interp": 8.70273335298355,
        "v_interp": -18.956725146122633,
        "w_interp": -0.004951182752539203
    },
    {
        "point_1": [
            48.96259,
            4.02518,
            158.8
        ],
        "point_2": [
            48.96259,
            4.02516,
            160.3
        ],
        "gh_interp": 0.5741653988575366,
        "u_interp": 8.672633516196834,
        "v_interp": -18.93083445932293,
        "w_interp": -0.004913065526520035
    },
    {
        "point_1": [
            48.96259,
            4.02516,
            160.3
        ],
        "point_2": [
            48.96259,
            4.02518,
            159.9
        ],
        "gh_interp": 0.5814194537867247,
        "u_interp": 8.71025831218023,
        "v_interp": -18.963197817822557,
        "w_interp": -0.004960712059043996
    },
    {
        "point_1": [
            48.96259,
            4.02518,
            159.9
        ],
        "point_2": [
            48.9626,
            4.02519,
            161.6
        ],
        "gh_interp": 0.5794850391389411,
        "u_interp": 8.700225033251323,
        "v_interp": -18.954567588889322,
        "w_interp": -0.004948006317037606
    },
    {
        "point_1": [
            48.9626,
            4.02519,
            161.6
        ],
        "point_2": [
            48.9626,
            4.02518,
            163.5
        ],
        "gh_interp": 0.6479405333114886,
        "u_interp": 13.587152175028105,
        "v_interp": -15.712351827747884,
        "w_interp": 0.010411399828361598
    },
    {
        "point_1": [
            48.9626,
            4.02518,
            163.5
        ],
        "point_2": [
            48.96261,
            4.02519,
            164.4
        ],
        "gh_interp": 0.6571093011504366,
        "u_interp": 13.63075396920864,
        "v_interp": -15.744575170687366,
        "w_interp": 0.010538727508890774
    },
    {
        "point_1": [
            48.96261,
            4.02519,
            164.4
        ],
        "point_2": [
            48.96261,
            4.02519,
            164.0
        ],
        "gh_interp": 0.6614524017057279,
        "u_interp": 13.651407450662578,
        "v_interp": -15.759838859448172,
        "w_interp": 0.010599040620720385
    }
]